module/__init__.py
ygorganization/__init__.py
ygorganization/asyncquery.py
ygorganization/dbstructure.py
ygorganization_api/__init__.py
yugiohdeck/__init__.py
yugiohdeck/config.py
yugiohdeck/core.py
yugiohdeck/ygoprodeck.py
yugiohdeck/ygoprodeck_dbstructure.py
yugiohdeck_api-0.0.1.dev7.dist-info/LICENSE
yugiohdeck_api-0.0.1.dev7.dist-info/METADATA
yugiohdeck_api-0.0.1.dev7.dist-info/WHEEL
yugiohdeck_api-0.0.1.dev7.dist-info/top_level.txt
yugiohdeck_api-0.0.1.dev7.dist-info/RECORD
