Metadata-Version: 2.1
Name: yugiohdeck-api
Version: 0.0.1.dev7
Summary: Transforms yugiohdeck.github.io links into card data (and back)
Home-page: https://yugiohdeck.github.io/
Author: gallantron
Author-email: treeston.mmoc@gmail.com
License: UNKNOWN
Platform: UNKNOWN
Classifier: Programming Language :: Python :: 3
Classifier: Operating System :: OS Independent
Requires-Python: >=3.6
Requires-Dist: ygorganization-api
